yamcs/kerberos.py
yamcs_client_kerberos-1.3.0.dist-info/METADATA
yamcs_client_kerberos-1.3.0.dist-info/WHEEL
yamcs_client_kerberos-1.3.0.dist-info/top_level.txt
yamcs_client_kerberos-1.3.0.dist-info/RECORD
