Metadata-Version: 2.1
Name: yamcs-client-kerberos
Version: 1.3.0
Summary: Kerberos integration for Yamcs API client library
Home-page: https://github.com/yamcs/python-yamcs-client/yamcs-client-kerberos
Author: Space Applications Services
Author-email: yamcs@spaceapplications.com
License: LGPL
Platform: Posix; MacOS X; Windows
Classifier: Development Status :: 5 - Production/Stable
Classifier: Intended Audience :: Developers
Classifier: License :: OSI Approved :: GNU Lesser General Public License v3 (LGPLv3)
Classifier: Programming Language :: Python
Classifier: Programming Language :: Python :: 3
Classifier: Programming Language :: Python :: 3.8
Classifier: Programming Language :: Python :: 3.9
Classifier: Programming Language :: Python :: 3.10
Classifier: Programming Language :: Python :: 3.11
Classifier: Programming Language :: Python :: 3.12
Classifier: Programming Language :: Python :: 3.13
Classifier: Operating System :: OS Independent
Requires-Python: >=3.8
Requires-Dist: requests-kerberos
Requires-Dist: yamcs-client>=1.11.0
